ansinject/__init__.py
ansinject/__main__.py
ansinject/ansinject.py
ansinject/cli.py
ansinject/config.py
ansinject/network_security_config.xml
tests/cli_test.py
ansinject-0.2.0.dist-info/LICENSE
ansinject-0.2.0.dist-info/METADATA
ansinject-0.2.0.dist-info/WHEEL
ansinject-0.2.0.dist-info/entry_points.txt
ansinject-0.2.0.dist-info/top_level.txt
ansinject-0.2.0.dist-info/RECORD
